CocoToSTPhoto/CocoToSTPhoto.py
CocoToSTPhoto/__init__.py
cocotostphoto-0.0.1.dist-info/LICENSE
cocotostphoto-0.0.1.dist-info/METADATA
cocotostphoto-0.0.1.dist-info/WHEEL
cocotostphoto-0.0.1.dist-info/top_level.txt
cocotostphoto-0.0.1.dist-info/RECORD
