Metadata-Version: 2.1
Name: cocotostphoto
Version: 0.0.1
Summary: COCO DataSet instances to STPhoto
Home-page: https://github.com/Sotaneum/CocoToSTPhoto
Author: Donggun LEE
Author-email: gnyotnu39@gmail.com
License: MIT
Platform: UNKNOWN
Classifier: License :: OSI Approved :: MIT License
